[
  {
    "difficulty": "Hard",
    "title": "Maximum Profit in Job Scheduling",
    "frequency": "100.0",
    "acceptanceRate": "0.5441727193976145",
    "link": "https://leetcode.com/problems/maximum-profit-in-job-scheduling",
    "topics": [
      "Array",
      "Binary Search",
      "Dynamic Programming",
      "Sorting"
    ]
  },
  {
    "difficulty": "Medium",
    "title": "Non-overlapping Intervals",
    "frequency": "100.0",
    "acceptanceRate": "0.5550325870996576",
    "link": "https://leetcode.com/problems/non-overlapping-intervals",
    "topics": [
      "Array",
      "Dynamic Programming",
      "Greedy",
      "Sorting"
    ]
  }
]
