[
  {
    "difficulty": "Medium",
    "title": "Decode String",
    "frequency": "100.0",
    "acceptanceRate": "0.611527047281157",
    "link": "https://leetcode.com/problems/decode-string",
    "topics": [
      "String",
      "Stack",
      "Recursion"
    ],
    "id": "Flexport-Decode String",
    "company": "Flexport",
    "timeframe": "90"
  },
  {
    "difficulty": "Medium",
    "title": "Clone Graph",
    "frequency": "100.0",
    "acceptanceRate": "0.6238596161697385",
    "link": "https://leetcode.com/problems/clone-graph",
    "topics": [
      "Hash Table",
      "Depth-First Search",
      "Breadth-First Search",
      "Graph"
    ],
    "id": "Flexport-Clone Graph",
    "company": "Flexport",
    "timeframe": "90"
  },
  {
    "difficulty": "Medium",
    "title": "Letter Combinations of a Phone Number",
    "frequency": "67.3",
    "acceptanceRate": "0.6385757154093107",
    "link": "https://leetcode.com/problems/letter-combinations-of-a-phone-number",
    "topics": [
      "Hash Table",
      "String",
      "Backtracking"
    ],
    "id": "Flexport-Letter Combinations of a Phone Number",
    "company": "Flexport",
    "timeframe": "180"
  },
  {
    "difficulty": "Medium",
    "title": "Validate IP Address",
    "frequency": "67.3",
    "acceptanceRate": "0.27817524620453365",
    "link": "https://leetcode.com/problems/validate-ip-address",
    "topics": [
      "String"
    ],
    "id": "Flexport-Validate IP Address",
    "company": "Flexport",
    "timeframe": "180"
  },
  {
    "difficulty": "Medium",
    "title": "My Calendar I",
    "frequency": "67.3",
    "acceptanceRate": "0.5814631853246708",
    "link": "https://leetcode.com/problems/my-calendar-i",
    "topics": [
      "Array",
      "Binary Search",
      "Design",
      "Segment Tree",
      "Ordered Set"
    ],
    "id": "Flexport-My Calendar I",
    "company": "Flexport",
    "timeframe": "180"
  },
  {
    "difficulty": "Medium",
    "title": "Bag of Tokens",
    "frequency": "92.6",
    "acceptanceRate": "0.5918662223280171",
    "link": "https://leetcode.com/problems/bag-of-tokens",
    "topics": [
      "Array",
      "Two Pointers",
      "Greedy",
      "Sorting"
    ],
    "id": "Flexport-Bag of Tokens",
    "company": "Flexport",
    "timeframe": "more_than_180"
  },
  {
    "difficulty": "Medium",
    "title": "Count Zero Request Servers",
    "frequency": "82.1",
    "acceptanceRate": "0.34117881058144933",
    "link": "https://leetcode.com/problems/count-zero-request-servers",
    "topics": [
      "Array",
      "Hash Table",
      "Sliding Window",
      "Sorting"
    ],
    "id": "Flexport-Count Zero Request Servers",
    "company": "Flexport",
    "timeframe": "more_than_180"
  },
  {
    "difficulty": "Medium",
    "title": "Time Based Key-Value Store",
    "frequency": "82.1",
    "acceptanceRate": "0.49366433435553103",
    "link": "https://leetcode.com/problems/time-based-key-value-store",
    "topics": [
      "Hash Table",
      "String",
      "Binary Search",
      "Design"
    ],
    "id": "Flexport-Time Based Key-Value Store",
    "company": "Flexport",
    "timeframe": "more_than_180"
  },
  {
    "difficulty": "Medium",
    "title": "Subarray Product Less Than K",
    "frequency": "82.1",
    "acceptanceRate": "0.5285358649789029",
    "link": "https://leetcode.com/problems/subarray-product-less-than-k",
    "topics": [
      "Array",
      "Binary Search",
      "Sliding Window",
      "Prefix Sum"
    ],
    "id": "Flexport-Subarray Product Less Than K",
    "company": "Flexport",
    "timeframe": "more_than_180"
  },
  {
    "difficulty": "Medium",
    "title": "Longest Increasing Subsequence",
    "frequency": "82.1",
    "acceptanceRate": "0.5780847126573901",
    "link": "https://leetcode.com/problems/longest-increasing-subsequence",
    "topics": [
      "Array",
      "Binary Search",
      "Dynamic Programming"
    ],
    "id": "Flexport-Longest Increasing Subsequence",
    "company": "Flexport",
    "timeframe": "more_than_180"
  }
]