[
  {
    "difficulty": "Medium",
    "title": "Maximum White Tiles Covered by a Carpet",
    "frequency": "100.0",
    "acceptanceRate": "0.34957825679475163",
    "link": "https://leetcode.com/problems/maximum-white-tiles-covered-by-a-carpet",
    "topics": [
      "Array",
      "Binary Search",
      "Greedy",
      "Sliding Window",
      "Sorting",
      "Prefix Sum"
    ],
    "id": "LTI-Maximum White Tiles Covered by a Carpet",
    "company": "LTI",
    "timeframe": "more_than_180"
  },
  {
    "difficulty": "Medium",
    "title": "Reverse Integer",
    "frequency": "89.0",
    "acceptanceRate": "0.3030900694104915",
    "link": "https://leetcode.com/problems/reverse-integer",
    "topics": [
      "Math"
    ],
    "id": "LTI-Reverse Integer",
    "company": "LTI",
    "timeframe": "more_than_180"
  },
  {
    "difficulty": "Hard",
    "title": "Closest Subsequence Sum",
    "frequency": "89.0",
    "acceptanceRate": "0.4160445423134075",
    "link": "https://leetcode.com/problems/closest-subsequence-sum",
    "topics": [
      "Array",
      "Two Pointers",
      "Dynamic Programming",
      "Bit Manipulation",
      "Sorting",
      "Bitmask"
    ],
    "id": "LTI-Closest Subsequence Sum",
    "company": "LTI",
    "timeframe": "more_than_180"
  },
  {
    "difficulty": "Medium",
    "title": "Count Zero Request Servers",
    "frequency": "89.0",
    "acceptanceRate": "0.3412006497165777",
    "link": "https://leetcode.com/problems/count-zero-request-servers",
    "topics": [
      "Array",
      "Hash Table",
      "Sliding Window",
      "Sorting"
    ],
    "id": "LTI-Count Zero Request Servers",
    "company": "LTI",
    "timeframe": "more_than_180"
  }
]