[
  {
    "difficulty": "Medium",
    "title": "Longest Substring Without Repeating Characters",
    "frequency": "100.0",
    "acceptanceRate": "0.3693619526562289",
    "link": "https://leetcode.com/problems/longest-substring-without-repeating-characters",
    "topics": [
      "Hash Table",
      "String",
      "Sliding Window"
    ],
    "id": "opentext-Longest Substring Without Repeating Characters",
    "company": "opentext",
    "timeframe": "more_than_180"
  },
  {
    "difficulty": "Easy",
    "title": "Largest 3-Same-Digit Number in String",
    "frequency": "88.8",
    "acceptanceRate": "0.6909566734515847",
    "link": "https://leetcode.com/problems/largest-3-same-digit-number-in-string",
    "topics": [
      "String"
    ],
    "id": "opentext-Largest 3-Same-Digit Number in String",
    "company": "opentext",
    "timeframe": "more_than_180"
  },
  {
    "difficulty": "Easy",
    "title": "Best Time to Buy and Sell Stock",
    "frequency": "88.8",
    "acceptanceRate": "0.5525972597748545",
    "link": "https://leetcode.com/problems/best-time-to-buy-and-sell-stock",
    "topics": [
      "Array",
      "Dynamic Programming"
    ],
    "id": "opentext-Best Time to Buy and Sell Stock",
    "company": "opentext",
    "timeframe": "more_than_180"
  },
  {
    "difficulty": "Easy",
    "title": "Valid Parentheses",
    "frequency": "65.5",
    "acceptanceRate": "0.42322927482455164",
    "link": "https://leetcode.com/problems/valid-parentheses",
    "topics": [
      "String",
      "Stack"
    ],
    "id": "opentext-Valid Parentheses",
    "company": "opentext",
    "timeframe": "all"
  }
]