[
  {
    "difficulty": "Medium",
    "title": "Determine if Two Strings Are Close",
    "frequency": "100.0",
    "acceptanceRate": "0.5413286903894399",
    "link": "https://leetcode.com/problems/determine-if-two-strings-are-close",
    "topics": [
      "Hash Table",
      "String",
      "Sorting",
      "Counting"
    ],
    "id": "Postmates-Determine if Two Strings Are Close",
    "company": "Postmates",
    "timeframe": "more_than_180"
  },
  {
    "difficulty": "Medium",
    "title": "Most Beautiful Item for Each Query",
    "frequency": "90.5",
    "acceptanceRate": "0.6204166873850132",
    "link": "https://leetcode.com/problems/most-beautiful-item-for-each-query",
    "topics": [
      "Array",
      "Binary Search",
      "Sorting"
    ],
    "id": "Postmates-Most Beautiful Item for Each Query",
    "company": "Postmates",
    "timeframe": "more_than_180"
  },
  {
    "difficulty": "Easy",
    "title": "Find the K-Beauty of a Number",
    "frequency": "90.5",
    "acceptanceRate": "0.6169555156399178",
    "link": "https://leetcode.com/problems/find-the-k-beauty-of-a-number",
    "topics": [
      "Math",
      "String",
      "Sliding Window"
    ],
    "id": "Postmates-Find the K-Beauty of a Number",
    "company": "Postmates",
    "timeframe": "more_than_180"
  }
]