[
  {
    "difficulty": "Easy",
    "title": "Best Time to Buy and Sell Stock",
    "frequency": "100.0",
    "acceptanceRate": "0.5525959754111676",
    "link": "https://leetcode.com/problems/best-time-to-buy-and-sell-stock",
    "topics": [
      "Array",
      "Dynamic Programming"
    ]
  },
  {
    "difficulty": "Easy",
    "title": "Minimum Absolute Difference",
    "frequency": "94.4",
    "acceptanceRate": "0.7065237783248814",
    "link": "https://leetcode.com/problems/minimum-absolute-difference",
    "topics": [
      "Array",
      "Sorting"
    ]
  },
  {
    "difficulty": "Medium",
    "title": "Daily Temperatures",
    "frequency": "94.4",
    "acceptanceRate": "0.6736502832589849",
    "link": "https://leetcode.com/problems/daily-temperatures",
    "topics": [
      "Array",
      "Stack",
      "Monotonic Stack"
    ]
  },
  {
    "difficulty": "Medium",
    "title": "Unique Paths II",
    "frequency": "76.9",
    "acceptanceRate": "0.4315424243087263",
    "link": "https://leetcode.com/problems/unique-paths-ii",
    "topics": [
      "Array",
      "Dynamic Programming",
      "Matrix"
    ]
  },
  {
    "difficulty": "Easy",
    "title": "Backspace String Compare",
    "frequency": "76.9",
    "acceptanceRate": "0.49481723692271534",
    "link": "https://leetcode.com/problems/backspace-string-compare",
    "topics": [
      "Two Pointers",
      "String",
      "Stack",
      "Simulation"
    ]
  },
  {
    "difficulty": "Medium",
    "title": "3Sum",
    "frequency": "76.9",
    "acceptanceRate": "0.37070964419376135",
    "link": "https://leetcode.com/problems/3sum",
    "topics": [
      "Array",
      "Two Pointers",
      "Sorting"
    ]
  },
  {
    "difficulty": "Easy",
    "title": "Find Pivot Index",
    "frequency": "76.9",
    "acceptanceRate": "0.6057036695144293",
    "link": "https://leetcode.com/problems/find-pivot-index",
    "topics": [
      "Array",
      "Prefix Sum"
    ]
  }
]
